datamodel/__init__.py
datamodel/abstract.py
datamodel/base.py
datamodel/converters.c
datamodel/converters.cp311-win32.pyd
datamodel/converters.html
datamodel/converters.pyx
datamodel/exceptions.c
datamodel/exceptions.cp311-win32.pyd
datamodel/exceptions.html
datamodel/exceptions.pxd
datamodel/exceptions.pyx
datamodel/fields.cp311-win32.pyd
datamodel/fields.cpp
datamodel/fields.html
datamodel/fields.pyx
datamodel/functions.cp311-win32.pyd
datamodel/functions.cpp
datamodel/functions.html
datamodel/functions.pxd
datamodel/functions.pyx
datamodel/models.py
datamodel/profiler.py
datamodel/py.typed
datamodel/rs_parsers.cp311-win32.pyd
datamodel/types.c
datamodel/types.cp311-win32.pyd
datamodel/types.html
datamodel/types.pyx
datamodel/validation.c
datamodel/validation.cp311-win32.pyd
datamodel/validation.html
datamodel/validation.pxd
datamodel/validation.pyx
datamodel/version.py
datamodel/adaptive/__init__.py
datamodel/adaptive/models.py
datamodel/aliases/__init__.py
datamodel/jsonld/__init__.py
datamodel/jsonld/models.py
datamodel/libs/__init__.py
datamodel/libs/mapping.c
datamodel/libs/mapping.cp311-win32.pyd
datamodel/libs/mapping.html
datamodel/libs/mapping.pxd
datamodel/libs/mapping.pyx
datamodel/libs/mutables.py
datamodel/parsers/__init__.py
datamodel/parsers/encoders.py
datamodel/parsers/json.cp311-win32.pyd
datamodel/parsers/json.cpp
datamodel/parsers/json.html
datamodel/parsers/json.pyx
datamodel/rs_core/Cargo.toml
datamodel/rs_core/src/lib.rs
datamodel/rs_parsers/Cargo.toml
datamodel/rs_parsers/src/lib.rs
datamodel/rs_validators/Cargo.toml
datamodel/rs_validators/src/lib.rs
datamodel/typedefs/__init__.py
datamodel/typedefs/singleton.c
datamodel/typedefs/singleton.cp311-win32.pyd
datamodel/typedefs/singleton.html
datamodel/typedefs/singleton.pxd
datamodel/typedefs/singleton.pyx
datamodel/typedefs/types.c
datamodel/typedefs/types.cp311-win32.pyd
datamodel/typedefs/types.html
datamodel/typedefs/types.pxd
datamodel/typedefs/types.pyx
examples/nn/examples.py
python_datamodel-0.10.17.dist-info/LICENSE
python_datamodel-0.10.17.dist-info/METADATA
python_datamodel-0.10.17.dist-info/WHEEL
python_datamodel-0.10.17.dist-info/top_level.txt
python_datamodel-0.10.17.dist-info/RECORD
