Metadata-Version: 2.1
Name: python-datamodel
Version: 0.10.17
Summary: simple library based on python +3.8 to use Dataclass-syntaxfor interacting with Data
Home-page: https://github.com/phenobarbital/python-datamodel
Author: Jesus Lara
Author-email: jesuslarag@gmail.com
License: BSD
Project-URL: Source, https://github.com/phenobarbital/datamodel
Project-URL: Funding, https://paypal.me/phenobarbital
Project-URL: Tracker, https://github.com/phenobarbital/datamodel/issues
Project-URL: Documentation, https://datamodel.readthedocs.io/en/latest/
Project-URL: Buy Me A Coffee!, https://www.buymeacoffee.com/phenobarbital
Project-URL: Say Thanks!, https://saythanks.io/to/phenobarbital
Keywords: asyncio,dataclass,dataclasses,data models
Platform: any
Classifier: Development Status :: 4 - Beta
Classifier: Intended Audience :: Developers
Classifier: Intended Audience :: System Administrators
Classifier: Topic :: Software Development :: Build Tools
Classifier: Topic :: Software Development :: Libraries :: Python Modules
Classifier: Programming Language :: Python :: 3
Classifier: Programming Language :: Python :: 3 :: Only
Classifier: Programming Language :: Python :: 3.10
Classifier: Programming Language :: Python :: 3.11
Classifier: Programming Language :: Python :: 3.12
Classifier: Programming Language :: Python :: 3.13
Classifier: Framework :: AsyncIO
Classifier: License :: OSI Approved :: BSD License
Classifier: Operating System :: OS Independent
Classifier: Topic :: System :: Systems Administration
Classifier: Topic :: Utilities
Classifier: Environment :: Web Environment
Requires-Python: >=3.10.0
License-File: LICENSE
Requires-Dist: numpy>=1.26.4
Requires-Dist: uvloop>=0.21.0
Requires-Dist: asyncio==3.4.3
Requires-Dist: faust-cchardet==2.1.19
Requires-Dist: ciso8601==2.3.2
Requires-Dist: objectpath==0.6.1
Requires-Dist: orjson>=3.10.11
Requires-Dist: typing-extensions>=4.9.0
Requires-Dist: asyncpg>=0.29.0
Requires-Dist: python-dateutil>=2.8.2
Requires-Dist: python-slugify==8.0.1
Requires-Dist: psycopg2-binary==2.9.10
Requires-Dist: msgspec==0.19.0
